stocxer_mcp/__init__.py
stocxer_mcp/server.py
stocxer_mcp-1.0.5.dist-info/licenses/LICENSE
stocxer_mcp-1.0.5.dist-info/METADATA
stocxer_mcp-1.0.5.dist-info/WHEEL
stocxer_mcp-1.0.5.dist-info/entry_points.txt
stocxer_mcp-1.0.5.dist-info/top_level.txt
stocxer_mcp-1.0.5.dist-info/RECORD
